{
  "subtitle": "GRN Month 8", 
  "description": "Ko  jas\u00fdpe memby\u2019i o\u00f1embosako\u00edma ou hagu\u00e2", 
  "language": "grn_PY", 
  "title": "JASY POAPY", 
  "primary_category": "990351f36f9d43e1b97d1b012120e018", 
  "created_at": "2015-04-15T11:14:18.842348+00:00", 
  "featured_in_category": false, 
  "modified_at": "2015-04-15T11:14:18.842591+00:00", 
  "_version": {
    "package_version": "1.0.1", 
    "language_version": "2.7.6", 
    "language": "python", 
    "language_version_string": "2.7.6 (default, Mar 22 2014, 23:03:41) \n[GCC 4.8.2]", 
    "package": "elastic-git"
  }, 
  "linked_pages": [], 
  "id": null, 
  "content": "Created by BabyCenter\r\n\r\nHete o\u00ee por\u00e2ma, oipyte pe mba\u2019e huk\u00fdva o\u00eeva memby ryr\u00fape. I\u00f1e\u2019a vev\u00fai okakuaa por\u00e2ma h\u00e2 omba\u2019apo hagu\u00e2 he\u00f1\u00f3i jave bebe\u2019i.\r\n\r\nEpytu\u2019u jepi, ha ejepy\u2019a \u00f1emongueta ne memby okakua\u00e1va nde pype. Ha\u2019e ne \u00f1and\u00fa ha voi  oiku\u00e1ata ne \u00f1e\u2019e. Ko jay\u00fdpe  opyvoita  gueteri nde  ryep\u00fdpe, \u00e1ga  tuichav\u00e9ma  ha  omyanyh\u00eama pa\u2019 \u00fb  o\u00eeh\u00e1m.\r\n\r\nEkarupa rire eguapy ha ejesareko, re\u00f1and\u00fata opyvoi meme, ha nere\u00f1anduv\u00e9i ramo pya\u2019e tereho ejehechauka doctorpe.\r\n\r\n", 
  "source": "e38d2c57dbbb497789df996764e4f2cb", 
  "featured": false, 
  "author_tags": [], 
  "image": null, 
  "published": null, 
  "position": 0, 
  "image_host": "http://thumbor.unicore.io", 
  "slug": "jasy-poapy", 
  "uuid": "a02114f3deb74655a61e6aabb67114ec"
}